Firmware/fifo/fifo.v
///////////////////////////////////////////////////////////////////////////////
// $Author: BH $    $Date: 2021-03-09 $    $Revision: 2 $
//
// Module: fifo.v
// Project: iCESDM (Sigma Delta Modulator for Lattice iCE40)
// Description: First-in-first-out queue.
// See also: based off the slides from https://zipcpu.com/tutorial/lsn-10-fifo.pdf
//
// Change history:  2021-03-09 Created file.
//                  2021-03-09 Added OVERWITE_OLD parameter.
//                  2021-05-07 Moved increment of addr_rd to read block to fix
//                             "multiply driven" error.
//
///////////////////////////////////////////////////////////////////////////////

`default_nettype none

`ifndef __FIFO_INCLUDE__
`define __FIFO_INCLUDE__
`endif

module fifo(i_clk, i_en, i_rst, i_wr, i_rd, i_data, o_full, o_empty, o_data);
    parameter ADDR_WIDTH = 8;
    parameter DATA_WIDTH = 8;
    parameter OVERWRITE_OLD = 0; // Set to 1 to keep most recent values in memory.
    input i_clk, i_en, i_rst, i_wr, i_rd;
    input [(DATA_WIDTH-1):0] i_data;
    output reg o_full, o_empty;
    output reg [(DATA_WIDTH-1):0] o_data;

    reg	[(DATA_WIDTH-1):0] mem [0:((1<<ADDR_WIDTH)-1)];
    reg	[ADDR_WIDTH:0] addr_rd, addr_wr, o_fill;

    initial
    begin
        addr_wr = 0;
        addr_rd = 0;
    end

    always @(*) 
        o_fill <= addr_wr - addr_rd;

    always @(*)
    begin
        o_empty = (o_fill == 0);
        o_full = (o_fill == {1'b1, {(ADDR_WIDTH){1'b0}}});
    end

    wire wr, rd;
    assign wr = i_wr && (!o_full || OVERWRITE_OLD);
    assign rd = i_rd && !o_empty;

    // Write
    always @(posedge i_clk)
    begin
        if (i_en)
        begin
            if (i_rst)
                addr_wr = 0;
            if (wr)
            begin
                addr_wr <= addr_wr + 1;
                mem[addr_wr[(ADDR_WIDTH-1):0]] <= i_data;
            end
        end
    end

    // Read
    always @(posedge i_clk)
    begin
        if (i_en)
        begin
            if (i_rst)
                addr_rd = 0;
            if (rd)
            begin
                addr_rd <= addr_rd + 1;
                o_data <= mem[addr_rd[(ADDR_WIDTH-1):0]];
            end
            else if (o_full && OVERWRITE_OLD)
                addr_rd = addr_rd + 1;
        end
    end

endmodule

Firmware/fifo/fifo_tb.v
///////////////////////////////////////////////////////////////////////////////
// $Author: BH $    $Date: 2021-03-09 $    $Revision: 0 $
//
// Module: fifo_tb.v
// Project: iCESDM (Sigma Delta Modulator for Lattice iCE40)
// Description: Test bench for first-in-first-out queue.
//
// Change history: 2021-03-09 Created file.
//
///////////////////////////////////////////////////////////////////////////////

`timescale 1ns/1ns
`include "fifo.v"
module fifo_tb();

reg clk, rst, en, wr, rd;
reg [7:0] din;
wire full, empty;
wire [7:0] dout;

fifo #(
    .DATA_WIDTH(8),
    .ADDR_WIDTH(2),
    .OVERWRITE_OLD(0)
) DUT (
    .i_clk(clk),
    .i_en(en),
    .i_rst(rst),
    .i_wr(wr),
    .i_rd(rd),
    .i_data(din),
    .o_full(full),
    .o_empty(empty),
    .o_data(dout)
);

always
#10 clk = ~clk;

initial
begin
    clk = 0;
    en = 1;
    rst = 0;
    din = 8'h11;
    rd = 1;
    wr = 0;
    #20 din = 8'h12;
    #20 din = 8'h13;
    #20 din = 8'h14;
    rd = 0;
    #20 din = 8'h15;
    wr = 1;
    #20 din = 8'h16;
    #20 din = 8'h17;
    #20 din = 8'h18;
    #20 din = 8'h19;
    #20 din = 8'h1a;
    rd = 1;
    #20 din = 8'h1b;
    #20 din = 8'h1c;
    wr = 0;
end

initial 
begin
    #2000 $stop;
end

initial
begin
    $dumpfile("out.vcd");
    $dumpvars(0,DUT);
end
 
initial
$monitor($stime,, rst,, clk,, din);

endmodule

Firmware/fifo/out.vcd
$date
	Tue Mar 09 16:14:14 2021
$end
$version
	Icarus Verilog
$end
$timescale
	1ns
$end
$scope module fifo_tb $end
$scope module DUT $end
$var wire 1 ! i_clk $end
$var wire 8 " i_data [7:0] $end
$var wire 1 # i_en $end
$var wire 1 $ i_rd $end
$var wire 1 % i_rst $end
$var wire 1 & i_wr $end
$var wire 1 ' rd $end
$var wire 1 ( wr $end
$var reg 3 ) addr_rd [2:0] $end
$var reg 3 * addr_wr [2:0] $end
$var reg 8 + o_data [7:0] $end
$var reg 1 , o_empty $end
$var reg 3 - o_fill [2:0] $end
$var reg 1 . o_full $end
$upscope $end
$upscope $end
$enddefinitions $end
#0
$dumpvars
0.
b0 -
1,
bx +
b0 *
b0 )
0(
0'
0&
0%
1$
1#
b10001 "
0!
$end
#10
1!
#20
0!
b10010 "
#30
1!
#40
0!
b10011 "
#50
1!
#60
0!
0$
b10100 "
#70
1!
#80
1(
0!
1&
b10101 "
#90
0,
b1 -
b1 *
1!
#100
0!
b10110 "
#110
b10 -
b10 *
1!
#120
0!
b10111 "
#130
b11 -
b11 *
1!
#140
0!
b11000 "
#150
0(
1.
b100 -
b100 *
1!
#160
0!
b11001 "
#170
1!
#180
1'
0!
1$
b11010 "
#190
1(
0.
b11 -
b10101 +
b1 )
1!
#200
0!
b11011 "
#210
b101 *
b10110 +
b10 )
1!
#220
0(
0!
0&
b11100 "
#230
b10 -
b10111 +
b11 )
1!
#240
0!
#250
b1 -
b11000 +
b100 )
1!
#260
0!
#270
0'
1,
b0 -
b11011 +
b101 )
1!
