Firmware/fir/coefficients.vh
parameter [(2*N_ADD-1):0] COEF_VEC = {2'b00, 2'b00, 2'b00, 2'b00, 2'b00, 2'b00, 2'b00, 2'b00, 2'b11, 2'b00, 2'b00, 2'b00, 2'b00, 2'b00, 2'b00, 2'b00, 2'b01, 2'b00, 2'b00, 2'b00, 2'b00, 2'b00, 2'b00, 2'b01, 2'b00, 2'b01, 2'b00, 2'b00, 2'b00, 2'b00, 2'b00, 2'b00, 2'b00, 2'b00, 2'b00, 2'b01, 2'b00, 2'b00, 2'b00, 2'b11, 2'b00, 2'b00, 2'b00, 2'b00, 2'b11, 2'b00, 2'b00, 2'b00, 2'b11, 2'b00, 2'b00, 2'b11, 2'b00, 2'b00, 2'b00, 2'b00, 2'b01, 2'b00, 2'b00, 2'b00, 2'b11, 2'b00, 2'b00, 2'b01, 2'b00, 2'b00, 2'b11, 2'b00, 2'b00, 2'b00, 2'b11, 2'b00, 2'b01, 2'b00, 2'b01, 2'b00, 2'b11, 2'b00, 2'b00, 2'b00, 2'b00, 2'b01, 2'b00, 2'b00, 2'b11, 2'b00, 2'b00, 2'b00, 2'b11, 2'b00, 2'b00, 2'b00, 2'b01, 2'b00, 2'b00, 2'b00, 2'b11, 2'b00, 2'b00, 2'b00, 2'b00, 2'b00, 2'b11, 2'b00, 2'b00, 2'b11, 2'b00, 2'b00, 2'b00, 2'b00, 2'b00, 2'b11, 2'b00, 2'b00, 2'b00, 2'b00, 2'b11, 2'b00, 2'b00, 2'b00, 2'b00, 2'b00, 2'b00, 2'b00, 2'b00, 2'b01, 2'b00, 2'b00, 2'b00, 2'b00, 2'b00, 2'b01, 2'b00, 2'b01, 2'b00, 2'b00, 2'b00, 2'b00, 2'b00, 2'b00, 2'b00, 2'b00, 2'b01, 2'b00, 2'b00, 2'b00, 2'b00, 2'b00, 2'b00, 2'b00, 2'b00, 2'b00, 2'b11};

Firmware/fir/fir_csd_logic_varcoef.v
///////////////////////////////////////////////////////////////////////////////
// $Author: BH $    $Date: 2021-12-01 $    $Revision: 0 $
//
// Module: FIR_CSD_logic_varcoef.v
// Project: iCESDM (Sigma Delta Modulator for Lattice iCE40)
// Description: Logic for multiplierless FIR filter with variable coefficients.
//
// Change history:  2021-12-01 Created file from fir_csd_logic.v.
//
///////////////////////////////////////////////////////////////////////////////

`ifndef __FIR_CSD_LOGIC_INCLUDE__
`define __FIR_CSD_LOGIC_INCLUDE__
`endif

module fir_csd_logic_varcoef(i_clk, i_en, i_data, o_data);
    parameter I_WIDTH = 16;
    parameter O_WIDTH = 16;
    parameter ORDER = 17;
    parameter N_SHIFT = 9;
    localparam N_ADD = ORDER*N_SHIFT;
    localparam INTERNAL_WIDTH = I_WIDTH + N_SHIFT;
    `include "coefficients.vh"
    
    input i_clk, i_en;
    input wire [(I_WIDTH*ORDER-1):0] i_data;
    output [(O_WIDTH-1):0] o_data;
    reg [(INTERNAL_WIDTH-1):0] filt;

    wire [(INTERNAL_WIDTH-1):0] to_add [0:(N_ADD-1)];

    genvar i, j;
    generate
        for (i=0; i<ORDER; i=i+1)
        begin
            for (j=0; j<N_SHIFT; j=j+1)
            begin
                if (COEF_VEC[2*(N_SHIFT*i+j)+:2]==2'b01) // +1
                    assign to_add[(N_SHIFT*i+j)] = i_data[(i*I_WIDTH)+:I_WIDTH] <<< j;
                else if (COEF_VEC[2*(N_SHIFT*i+j)+:2]==2'b11) // -1
                    assign to_add[(N_SHIFT*i+j)] = (-i_data[(i*I_WIDTH)+:I_WIDTH]) <<< j;
                else // 0
                    assign to_add[(N_SHIFT*i+j)] = {INTERNAL_WIDTH{1'b0}};
            end
        end
    endgenerate

    integer l;

    always @(posedge i_clk)
    begin
        filt = 0;
        for (l=0; l<N_ADD; l=l+1)
        begin
            filt = filt + to_add[l];
        end
    end

    assign o_data = filt[(INTERNAL_WIDTH-1)-:O_WIDTH];

endmodule

Firmware/shift/shift.v
///////////////////////////////////////////////////////////////////////////////
// $Author: BH $    $Date: 2018-11-11 $    $Revision: 0 $
//
// Module: shift.v
// Project: iCESDM (Sigma Delta Modulator for Lattice iCE40)
// Description: Shift register with parallel out.
//
// Change history:  2018-11-11 Created file.
//                  2018-11-12 Added parallel out functionality.
//                  2021-03-05 Added conditional compilation flag.
//
///////////////////////////////////////////////////////////////////////////////

`ifndef __SHIFT_INCLUDE__
`define __SHIFT_INCLUDE__
`endif

module shift(i_clk, i_en, i_rst, i_data, o_ser, o_par);
    parameter WIDTH = 1;
    parameter LENGTH = 2;
    input i_clk, i_en, i_rst;
    input [WIDTH-1:0] i_data;
    output [WIDTH-1:0] o_ser;
    output [LENGTH*WIDTH-1:0] o_par;
    reg [LENGTH*WIDTH-1:0] sreg;

    always @(posedge i_clk)
    begin
        if (i_en)
            if (i_rst)
                sreg <= 0;
            else
                sreg <= {sreg[(LENGTH-1)*WIDTH-1:0], i_data};
    end
    assign o_ser = sreg[(LENGTH*WIDTH-1):(LENGTH-1)*WIDTH];
    assign o_par = sreg;
endmodule

Firmware/fir/fir_csd_tb.v
///////////////////////////////////////////////////////////////////////////////
// $Author: BH $    $Date: 2021-12-01 $    $Revision: 0 $
//
// Module: fir_csd_tb.v
// Project: iCESDM (Sigma Delta Modulator for Lattice iCE40)
// Description: Test bench for multiplierless FIR filter.
//
// Change history: 2021-12-01 Created file.
//
///////////////////////////////////////////////////////////////////////////////

`timescale 1ns/1ns
`include "fir_csd_logic_varcoef.v"
`include "../shift/shift.v"
module fir_csd_tb();

reg clk, rst, en;
reg [15:0] din;
wire full, empty;
wire [23:0] dout;
wire [(16*17-1):0] delay;

shift #(
    .WIDTH(16),
    .LENGTH(17)
) delay_line (
    .i_clk(clk),
    .i_en(en),
    .i_rst(rst),
    .i_data(din),
    .o_par(delay)
);

fir_csd_logic_varcoef #(
    .I_WIDTH(16),
    .O_WIDTH(24),
    .ORDER(17),
    .N_SHIFT(9)
) DUT (
    .i_clk(clk),
    .i_en(en),
    .i_data(delay),
    .o_data(dout)
);

always
#10 clk = ~clk;

initial
begin
    clk = 0;
    en = 1;
    rst = 0;
    din=16'h0000;
    #400 din=16'h0001;
end

initial 
begin
    #10000 $stop;
end

initial
begin
    $dumpfile("out.vcd");
    $dumpvars(0);
end
 
initial
$monitor($stime,, rst,, clk,, din);

endmodule

Firmware/fir/out.vcd
$date
	Thu Dec 02 14:36:07 2021
$end
$version
	Icarus Verilog
$end
$timescale
	1ns
$end
$scope module fir_csd_tb $end
$var wire 24 ! dout [23:0] $end
$var wire 272 " delay [271:0] $end
$var reg 1 # clk $end
$var reg 16 $ din [15:0] $end
$var reg 1 % en $end
$var reg 1 & rst $end
$scope module DUT $end
$var wire 1 # i_clk $end
$var wire 1 % i_en $end
$var wire 24 ' o_data [23:0] $end
$var wire 272 ( i_data [271:0] $end
$var reg 25 ) filt [24:0] $end
$var integer 32 * l [31:0] $end
$scope begin genblk1[0] $end
$scope begin genblk2[0] $end
$scope begin genblk5 $end
$upscope $end
$upscope $end
$scope begin genblk2[1] $end
$scope begin genblk6 $end
$upscope $end
$upscope $end
$scope begin genblk2[2] $end
$scope begin genblk6 $end
$upscope $end
$upscope $end
$scope begin genblk2[3] $end
$scope begin genblk6 $end
$upscope $end
$upscope $end
$scope begin genblk2[4] $end
$scope begin genblk6 $end
$upscope $end
$upscope $end
$scope begin genblk2[5] $end
$scope begin genblk6 $end
$upscope $end
$upscope $end
$scope begin genblk2[6] $end
$scope begin genblk6 $end
$upscope $end
$upscope $end
$scope begin genblk2[7] $end
$scope begin genblk6 $end
$upscope $end
$upscope $end
$scope begin genblk2[8] $end
$scope begin genblk6 $end
$upscope $end
$upscope $end
$upscope $end
$scope begin genblk1[1] $end
$scope begin genblk2[0] $end
$scope begin genblk6 $end
$upscope $end
$upscope $end
$scope begin genblk2[1] $end
$scope begin genblk3 $end
$upscope $end
$upscope $end
$scope begin genblk2[2] $end
$scope begin genblk6 $end
$upscope $end
$upscope $end
$scope begin genblk2[3] $end
$scope begin genblk6 $end
$upscope $end
$upscope $end
$scope begin genblk2[4] $end
$scope begin genblk6 $end
$upscope $end
$upscope $end
$scope begin genblk2[5] $end
$scope begin genblk6 $end
$upscope $end
$upscope $end
$scope begin genblk2[6] $end
$scope begin genblk6 $end
$upscope $end
$upscope $end
$scope begin genblk2[7] $end
$scope begin genblk6 $end
$upscope $end
$upscope $end
$scope begin genblk2[8] $end
$scope begin genblk6 $end
$upscope $end
$upscope $end
$upscope $end
$scope begin genblk1[2] $end
$scope begin genblk2[0] $end
$scope begin genblk6 $end
$upscope $end
$upscope $end
$scope begin genblk2[1] $end
$scope begin genblk3 $end
$upscope $end
$upscope $end
$scope begin genblk2[2] $end
$scope begin genblk6 $end
$upscope $end
$upscope $end
$scope begin genblk2[3] $end
$scope begin genblk3 $end
$upscope $end
$upscope $end
$scope begin genblk2[4] $end
$scope begin genblk6 $end
$upscope $end
$upscope $end
$scope begin genblk2[5] $end
$scope begin genblk6 $end
$upscope $end
$upscope $end
$scope begin genblk2[6] $end
$scope begin genblk6 $end
$upscope $end
$upscope $end
$scope begin genblk2[7] $end
$scope begin genblk6 $end
$upscope $end
$upscope $end
$scope begin genblk2[8] $end
$scope begin genblk6 $end
$upscope $end
$upscope $end
$upscope $end
$scope begin genblk1[3] $end
$scope begin genblk2[0] $end
$scope begin genblk3 $end
$upscope $end
$upscope $end
$scope begin genblk2[1] $end
$scope begin genblk6 $end
$upscope $end
$upscope $end
$scope begin genblk2[2] $end
$scope begin genblk6 $end
$upscope $end
$upscope $end
$scope begin genblk2[3] $end
$scope begin genblk6 $end
$upscope $end
$upscope $end
$scope begin genblk2[4] $end
$scope begin genblk6 $end
$upscope $end
$upscope $end
$scope begin genblk2[5] $end
$scope begin genblk6 $end
$upscope $end
$upscope $end
$scope begin genblk2[6] $end
$scope begin genblk6 $end
$upscope $end
$upscope $end
$scope begin genblk2[7] $end
$scope begin genblk6 $end
$upscope $end
$upscope $end
$scope begin genblk2[8] $end
$scope begin genblk6 $end
$upscope $end
$upscope $end
$upscope $end
$scope begin genblk1[4] $end
$scope begin genblk2[0] $end
$scope begin genblk5 $end
$upscope $end
$upscope $end
$scope begin genblk2[1] $end
$scope begin genblk6 $end
$upscope $end
$upscope $end
$scope begin genblk2[2] $end
$scope begin genblk6 $end
$upscope $end
$upscope $end
$scope begin genblk2[3] $end
$scope begin genblk6 $end
$upscope $end
$upscope $end
$scope begin genblk2[4] $end
$scope begin genblk6 $end
$upscope $end
$upscope $end
$scope begin genblk2[5] $end
$scope begin genblk5 $end
$upscope $end
$upscope $end
$scope begin genblk2[6] $end
$scope begin genblk6 $end
$upscope $end
$upscope $end
$scope begin genblk2[7] $end
$scope begin genblk6 $end
$upscope $end
$upscope $end
$scope begin genblk2[8] $end
$scope begin genblk6 $end
$upscope $end
$upscope $end
$upscope $end
$scope begin genblk1[5] $end
$scope begin genblk2[0] $end
$scope begin genblk6 $end
$upscope $end
$upscope $end
$scope begin genblk2[1] $end
$scope begin genblk6 $end
$upscope $end
$upscope $end
$scope begin genblk2[2] $end
$scope begin genblk5 $end
$upscope $end
$upscope $end
$scope begin genblk2[3] $end
$scope begin genblk6 $end
$upscope $end
$upscope $end
$scope begin genblk2[4] $end
$scope begin genblk6 $end
$upscope $end
$upscope $end
$scope begin genblk2[5] $end
$scope begin genblk5 $end
$upscope $end
$upscope $end
$scope begin genblk2[6] $end
$scope begin genblk6 $end
$upscope $end
$upscope $end
$scope begin genblk2[7] $end
$scope begin genblk6 $end
$upscope $end
$upscope $end
$scope begin genblk2[8] $end
$scope begin genblk6 $end
$upscope $end
$upscope $end
$upscope $end
$scope begin genblk1[6] $end
$scope begin genblk2[0] $end
$scope begin genblk6 $end
$upscope $end
$upscope $end
$scope begin genblk2[1] $end
$scope begin genblk6 $end
$upscope $end
$upscope $end
$scope begin genblk2[2] $end
$scope begin genblk5 $end
$upscope $end
$upscope $end
$scope begin genblk2[3] $end
$scope begin genblk6 $end
$upscope $end
$upscope $end
$scope begin genblk2[4] $end
$scope begin genblk6 $end
$upscope $end
$upscope $end
$scope begin genblk2[5] $end
$scope begin genblk6 $end
$upscope $end
$upscope $end
$scope begin genblk2[6] $end
$scope begin genblk3 $end
$upscope $end
$upscope $end
$scope begin genblk2[7] $end
$scope begin genblk6 $end
$upscope $end
$upscope $end
$scope begin genblk2[8] $end
$scope begin genblk6 $end
$upscope $end
$upscope $end
$upscope $end
$scope begin genblk1[7] $end
$scope begin genblk2[0] $end
$scope begin genblk6 $end
$upscope $end
$upscope $end
$scope begin genblk2[1] $end
$scope begin genblk5 $end
$upscope $end
$upscope $end
$scope begin genblk2[2] $end
$scope begin genblk6 $end
$upscope $end
$upscope $end
$scope begin genblk2[3] $end
$scope begin genblk6 $end
$upscope $end
$upscope $end
$scope begin genblk2[4] $end
$scope begin genblk6 $end
$upscope $end
$upscope $end
$scope begin genblk2[5] $end
$scope begin genblk5 $end
$upscope $end
$upscope $end
$scope begin genblk2[6] $end
$scope begin genblk6 $end
$upscope $end
$upscope $end
$scope begin genblk2[7] $end
$scope begin genblk6 $end
$upscope $end
$upscope $end
$scope begin genblk2[8] $end
$scope begin genblk3 $end
$upscope $end
$upscope $end
$upscope $end
$scope begin genblk1[8] $end
$scope begin genblk2[0] $end
$scope begin genblk6 $end
$upscope $end
$upscope $end
$scope begin genblk2[1] $end
$scope begin genblk6 $end
$upscope $end
$upscope $end
$scope begin genblk2[2] $end
$scope begin genblk6 $end
$upscope $end
$upscope $end
$scope begin genblk2[3] $end
$scope begin genblk6 $end
$upscope $end
$upscope $end
$scope begin genblk2[4] $end
$scope begin genblk5 $end
$upscope $end
$upscope $end
$scope begin genblk2[5] $end
$scope begin genblk6 $end
$upscope $end
$upscope $end
$scope begin genblk2[6] $end
$scope begin genblk3 $end
$upscope $end
$upscope $end
$scope begin genblk2[7] $end
$scope begin genblk6 $end
$upscope $end
$upscope $end
$scope begin genblk2[8] $end
$scope begin genblk3 $end
$upscope $end
$upscope $end
$upscope $end
$scope begin genblk1[9] $end
$scope begin genblk2[0] $end
$scope begin genblk6 $end
$upscope $end
$upscope $end
$scope begin genblk2[1] $end
$scope begin genblk5 $end
$upscope $end
$upscope $end
$scope begin genblk2[2] $end
$scope begin genblk6 $end
$upscope $end
$upscope $end
$scope begin genblk2[3] $end
$scope begin genblk6 $end
$upscope $end
$upscope $end
$scope begin genblk2[4] $end
$scope begin genblk6 $end
$upscope $end
$upscope $end
$scope begin genblk2[5] $end
$scope begin genblk5 $end
$upscope $end
$upscope $end
$scope begin genblk2[6] $end
$scope begin genblk6 $end
$upscope $end
$upscope $end
$scope begin genblk2[7] $end
$scope begin genblk6 $end
$upscope $end
$upscope $end
$scope begin genblk2[8] $end
$scope begin genblk3 $end
$upscope $end
$upscope $end
$upscope $end
$scope begin genblk1[10] $end
$scope begin genblk2[0] $end
$scope begin genblk6 $end
$upscope $end
$upscope $end
$scope begin genblk2[1] $end
$scope begin genblk6 $end
$upscope $end
$upscope $end
$scope begin genblk2[2] $end
$scope begin genblk5 $end
$upscope $end
$upscope $end
$scope begin genblk2[3] $end
$scope begin genblk6 $end
$upscope $end
$upscope $end
$scope begin genblk2[4] $end
$scope begin genblk6 $end
$upscope $end
$upscope $end
$scope begin genblk2[5] $end
$scope begin genblk6 $end
$upscope $end
$upscope $end
$scope begin genblk2[6] $end
$scope begin genblk3 $end
$upscope $end
$upscope $end
$scope begin genblk2[7] $end
$scope begin genblk6 $end
$upscope $end
$upscope $end
$scope begin genblk2[8] $end
$scope begin genblk6 $end
$upscope $end
$upscope $end
$upscope $end
$scope begin genblk1[11] $end
$scope begin genblk2[0] $end
$scope begin genblk6 $end
$upscope $end
$upscope $end
$scope begin genblk2[1] $end
$scope begin genblk6 $end
$upscope $end
$upscope $end
$scope begin genblk2[2] $end
$scope begin genblk5 $end
$upscope $end
$upscope $end
$scope begin genblk2[3] $end
$scope begin genblk6 $end
$upscope $end
$upscope $end
$scope begin genblk2[4] $end
$scope begin genblk6 $end
$upscope $end
$upscope $end
$scope begin genblk2[5] $end
$scope begin genblk5 $end
$upscope $end
$upscope $end
$scope begin genblk2[6] $end
$scope begin genblk6 $end
$upscope $end
$upscope $end
$scope begin genblk2[7] $end
$scope begin genblk6 $end
$upscope $end
$upscope $end
$scope begin genblk2[8] $end
$scope begin genblk6 $end
$upscope $end
$upscope $end
$upscope $end
$scope begin genblk1[12] $end
$scope begin genblk2[0] $end
$scope begin genblk5 $end
$upscope $end
$upscope $end
$scope begin genblk2[1] $end
$scope begin genblk6 $end
$upscope $end
$upscope $end
$scope begin genblk2[2] $end
$scope begin genblk6 $end
$upscope $end
$upscope $end
$scope begin genblk2[3] $end
$scope begin genblk6 $end
$upscope $end
$upscope $end
$scope begin genblk2[4] $end
$scope begin genblk6 $end
$upscope $end
$upscope $end
$scope begin genblk2[5] $end
$scope begin genblk5 $end
$upscope $end
$upscope $end
$scope begin genblk2[6] $end
$scope begin genblk6 $end
$upscope $end
$upscope $end
$scope begin genblk2[7] $end
$scope begin genblk6 $end
$upscope $end
$upscope $end
$scope begin genblk2[8] $end
$scope begin genblk6 $end
$upscope $end
$upscope $end
$upscope $end
$scope begin genblk1[13] $end
$scope begin genblk2[0] $end
$scope begin genblk3 $end
$upscope $end
$upscope $end
$scope begin genblk2[1] $end
$scope begin genblk6 $end
$upscope $end
$upscope $end
$scope begin genblk2[2] $end
$scope begin genblk6 $end
$upscope $end
$upscope $end
$scope begin genblk2[3] $end
$scope begin genblk6 $end
$upscope $end
$upscope $end
$scope begin genblk2[4] $end
$scope begin genblk6 $end
$upscope $end
$upscope $end
$scope begin genblk2[5] $end
$scope begin genblk6 $end
$upscope $end
$upscope $end
$scope begin genblk2[6] $end
$scope begin genblk6 $end
$upscope $end
$upscope $end
$scope begin genblk2[7] $end
$scope begin genblk6 $end
$upscope $end
$upscope $end
$scope begin genblk2[8] $end
$scope begin genblk6 $end
$upscope $end
$upscope $end
$upscope $end
$scope begin genblk1[14] $end
$scope begin genblk2[0] $end
$scope begin genblk6 $end
$upscope $end
$upscope $end
$scope begin genblk2[1] $end
$scope begin genblk3 $end
$upscope $end
$upscope $end
$scope begin genblk2[2] $end
$scope begin genblk6 $end
$upscope $end
$upscope $end
$scope begin genblk2[3] $end
$scope begin genblk3 $end
$upscope $end
$upscope $end
$scope begin genblk2[4] $end
$scope begin genblk6 $end
$upscope $end
$upscope $end
$scope begin genblk2[5] $end
$scope begin genblk6 $end
$upscope $end
$upscope $end
$scope begin genblk2[6] $end
$scope begin genblk6 $end
$upscope $end
$upscope $end
$scope begin genblk2[7] $end
$scope begin genblk6 $end
$upscope $end
$upscope $end
$scope begin genblk2[8] $end
$scope begin genblk6 $end
$upscope $end
$upscope $end
$upscope $end
$scope begin genblk1[15] $end
$scope begin genblk2[0] $end
$scope begin genblk6 $end
$upscope $end
$upscope $end
$scope begin genblk2[1] $end
$scope begin genblk3 $end
$upscope $end
$upscope $end
$scope begin genblk2[2] $end
$scope begin genblk6 $end
$upscope $end
$upscope $end
$scope begin genblk2[3] $end
$scope begin genblk6 $end
$upscope $end
$upscope $end
$scope begin genblk2[4] $end
$scope begin genblk6 $end
$upscope $end
$upscope $end
$scope begin genblk2[5] $end
$scope begin genblk6 $end
$upscope $end
$upscope $end
$scope begin genblk2[6] $end
$scope begin genblk6 $end
$upscope $end
$upscope $end
$scope begin genblk2[7] $end
$scope begin genblk6 $end
$upscope $end
$upscope $end
$scope begin genblk2[8] $end
$scope begin genblk6 $end
$upscope $end
$upscope $end
$upscope $end
$scope begin genblk1[16] $end
$scope begin genblk2[0] $end
$scope begin genblk5 $end
$upscope $end
$upscope $end
$scope begin genblk2[1] $end
$scope begin genblk6 $end
$upscope $end
$upscope $end
$scope begin genblk2[2] $end
$scope begin genblk6 $end
$upscope $end
$upscope $end
$scope begin genblk2[3] $end
$scope begin genblk6 $end
$upscope $end
$upscope $end
$scope begin genblk2[4] $end
$scope begin genblk6 $end
$upscope $end
$upscope $end
$scope begin genblk2[5] $end
$scope begin genblk6 $end
$upscope $end
$upscope $end
$scope begin genblk2[6] $end
$scope begin genblk6 $end
$upscope $end
$upscope $end
$scope begin genblk2[7] $end
$scope begin genblk6 $end
$upscope $end
$upscope $end
$scope begin genblk2[8] $end
$scope begin genblk6 $end
$upscope $end
$upscope $end
$upscope $end
$upscope $end
$scope module delay_line $end
$var wire 1 # i_clk $end
$var wire 16 + i_data [15:0] $end
$var wire 1 % i_en $end
$var wire 1 & i_rst $end
$var wire 272 , o_par [271:0] $end
$var wire 16 - o_ser [15:0] $end
$var reg 272 . sreg [271:0] $end
$upscope $end
$upscope $end
$enddefinitions $end
#0
$dumpvars
bx .
bx -
bx ,
b0 +
bx *
bx )
bx (
bx '
0&
1%
b0 $
0#
bx "
bx !
$end
#10
bx0000000000000000 "
bx0000000000000000 (
bx0000000000000000 ,
bx0000000000000000 .
b10011001 *
bx )
1#
#20
0#
#30
bx00000000000000000000000000000000 "
bx00000000000000000000000000000000 (
bx00000000000000000000000000000000 ,
bx00000000000000000000000000000000 .
b10011001 *
bx )
1#
#40
0#
#50
bx000000000000000000000000000000000000000000000000 "
bx000000000000000000000000000000000000000000000000 (
bx000000000000000000000000000000000000000000000000 ,
bx000000000000000000000000000000000000000000000000 .
b10011001 *
bx )
1#
#60
0#
#70
bx0000000000000000000000000000000000000000000000000000000000000000 "
bx0000000000000000000000000000000000000000000000000000000000000000 (
bx0000000000000000000000000000000000000000000000000000000000000000 ,
bx0000000000000000000000000000000000000000000000000000000000000000 .
b10011001 *
bx )
1#
#80
0#
#90
bx00000000000000000000000000000000000000000000000000000000000000000000000000000000 "
bx00000000000000000000000000000000000000000000000000000000000000000000000000000000 (
bx00000000000000000000000000000000000000000000000000000000000000000000000000000000 ,
bx00000000000000000000000000000000000000000000000000000000000000000000000000000000 .
b10011001 *
bx )
1#
#100
0#
#110
bx000000000000000000000000000000000000000000000000000000000000000000000000000000000000000000000000 "
bx000000000000000000000000000000000000000000000000000000000000000000000000000000000000000000000000 (
bx000000000000000000000000000000000000000000000000000000000000000000000000000000000000000000000000 ,
bx000000000000000000000000000000000000000000000000000000000000000000000000000000000000000000000000 .
b10011001 *
bx )
1#
#120
0#
#130
bx0000000000000000000000000000000000000000000000000000000000000000000000000000000000000000000000000000000000000000 "
bx0000000000000000000000000000000000000000000000000000000000000000000000000000000000000000000000000000000000000000 (
bx0000000000000000000000000000000000000000000000000000000000000000000000000000000000000000000000000000000000000000 ,
bx0000000000000000000000000000000000000000000000000000000000000000000000000000000000000000000000000000000000000000 .
b10011001 *
bx )
1#
#140
0#
#150
bx00000000000000000000000000000000000000000000000000000000000000000000000000000000000000000000000000000000000000000000000000000000 "
bx00000000000000000000000000000000000000000000000000000000000000000000000000000000000000000000000000000000000000000000000000000000 (
bx00000000000000000000000000000000000000000000000000000000000000000000000000000000000000000000000000000000000000000000000000000000 ,
bx00000000000000000000000000000000000000000000000000000000000000000000000000000000000000000000000000000000000000000000000000000000 .
b10011001 *
bx )
1#
#160
0#
#170
bx000000000000000000000000000000000000000000000000000000000000000000000000000000000000000000000000000000000000000000000000000000000000000000000000 "
bx000000000000000000000000000000000000000000000000000000000000000000000000000000000000000000000000000000000000000000000000000000000000000000000000 (
bx000000000000000000000000000000000000000000000000000000000000000000000000000000000000000000000000000000000000000000000000000000000000000000000000 ,
bx000000000000000000000000000000000000000000000000000000000000000000000000000000000000000000000000000000000000000000000000000000000000000000000000 .
b10011001 *
bx )
1#
#180
0#
#190
bx0000000000000000000000000000000000000000000000000000000000000000000000000000000000000000000000000000000000000000000000000000000000000000000000000000000000000000 "
bx0000000000000000000000000000000000000000000000000000000000000000000000000000000000000000000000000000000000000000000000000000000000000000000000000000000000000000 (
bx0000000000000000000000000000000000000000000000000000000000000000000000000000000000000000000000000000000000000000000000000000000000000000000000000000000000000000 ,
bx0000000000000000000000000000000000000000000000000000000000000000000000000000000000000000000000000000000000000000000000000000000000000000000000000000000000000000 .
b10011001 *
bx )
1#
#200
0#
#210
bx00000000000000000000000000000000000000000000000000000000000000000000000000000000000000000000000000000000000000000000000000000000000000000000000000000000000000000000000000000000 "
bx00000000000000000000000000000000000000000000000000000000000000000000000000000000000000000000000000000000000000000000000000000000000000000000000000000000000000000000000000000000 (
bx00000000000000000000000000000000000000000000000000000000000000000000000000000000000000000000000000000000000000000000000000000000000000000000000000000000000000000000000000000000 ,
bx00000000000000000000000000000000000000000000000000000000000000000000000000000000000000000000000000000000000000000000000000000000000000000000000000000000000000000000000000000000 .
b10011001 *
bx )
1#
#220
0#
#230
bx000000000000000000000000000000000000000000000000000000000000000000000000000000000000000000000000000000000000000000000000000000000000000000000000000000000000000000000000000000000000000000000000 "
bx000000000000000000000000000000000000000000000000000000000000000000000000000000000000000000000000000000000000000000000000000000000000000000000000000000000000000000000000000000000000000000000000 (
bx000000000000000000000000000000000000000000000000000000000000000000000000000000000000000000000000000000000000000000000000000000000000000000000000000000000000000000000000000000000000000000000000 ,
bx000000000000000000000000000000000000000000000000000000000000000000000000000000000000000000000000000000000000000000000000000000000000000000000000000000000000000000000000000000000000000000000000 .
b10011001 *
bx )
1#
#240
0#
#250
bx0000000000000000000000000000000000000000000000000000000000000000000000000000000000000000000000000000000000000000000000000000000000000000000000000000000000000000000000000000000000000000000000000000000000000000 "
bx0000000000000000000000000000000000000000000000000000000000000000000000000000000000000000000000000000000000000000000000000000000000000000000000000000000000000000000000000000000000000000000000000000000000000000 (
bx0000000000000000000000000000000000000000000000000000000000000000000000000000000000000000000000000000000000000000000000000000000000000000000000000000000000000000000000000000000000000000000000000000000000000000 ,
bx0000000000000000000000000000000000000000000000000000000000000000000000000000000000000000000000000000000000000000000000000000000000000000000000000000000000000000000000000000000000000000000000000000000000000000 .
b10011001 *
bx )
1#
#260
0#
#270
bx00000000000000000000000000000000000000000000000000000000000000000000000000000000000000000000000000000000000000000000000000000000000000000000000000000000000000000000000000000000000000000000000000000000000000000000000000000000 "
bx00000000000000000000000000000000000000000000000000000000000000000000000000000000000000000000000000000000000000000000000000000000000000000000000000000000000000000000000000000000000000000000000000000000000000000000000000000000 (
bx00000000000000000000000000000000000000000000000000000000000000000000000000000000000000000000000000000000000000000000000000000000000000000000000000000000000000000000000000000000000000000000000000000000000000000000000000000000 ,
bx00000000000000000000000000000000000000000000000000000000000000000000000000000000000000000000000000000000000000000000000000000000000000000000000000000000000000000000000000000000000000000000000000000000000000000000000000000000 .
b10011001 *
bx )
1#
#280
0#
#290
bx000000000000000000000000000000000000000000000000000000000000000000000000000000000000000000000000000000000000000000000000000000000000000000000000000000000000000000000000000000000000000000000000000000000000000000000000000000000000000000000000 "
bx000000000000000000000000000000000000000000000000000000000000000000000000000000000000000000000000000000000000000000000000000000000000000000000000000000000000000000000000000000000000000000000000000000000000000000000000000000000000000000000000 (
bx000000000000000000000000000000000000000000000000000000000000000000000000000000000000000000000000000000000000000000000000000000000000000000000000000000000000000000000000000000000000000000000000000000000000000000000000000000000000000000000000 ,
bx000000000000000000000000000000000000000000000000000000000000000000000000000000000000000000000000000000000000000000000000000000000000000000000000000000000000000000000000000000000000000000000000000000000000000000000000000000000000000000000000 .
b10011001 *
bx )
1#
#300
0#
#310
bx0000000000000000000000000000000000000000000000000000000000000000000000000000000000000000000000000000000000000000000000000000000000000000000000000000000000000000000000000000000000000000000000000000000000000000000000000000000000000000000000000000000000000000 "
bx0000000000000000000000000000000000000000000000000000000000000000000000000000000000000000000000000000000000000000000000000000000000000000000000000000000000000000000000000000000000000000000000000000000000000000000000000000000000000000000000000000000000000000 (
bx0000000000000000000000000000000000000000000000000000000000000000000000000000000000000000000000000000000000000000000000000000000000000000000000000000000000000000000000000000000000000000000000000000000000000000000000000000000000000000000000000000000000000000 ,
bx0000000000000000000000000000000000000000000000000000000000000000000000000000000000000000000000000000000000000000000000000000000000000000000000000000000000000000000000000000000000000000000000000000000000000000000000000000000000000000000000000000000000000000 .
b10011001 *
bx )
1#
#320
0#
#330
b0 -
b0 "
b0 (
b0 ,
b0 .
b10011001 *
bx )
1#
#340
0#
#350
b0 !
b0 '
b10011001 *
b0 )
1#
#360
0#
#370
b10011001 *
1#
#380
0#
#390
b10011001 *
1#
#400
0#
b1 $
b1 +
#410
b1 "
b1 (
b1 ,
b1 .
b10011001 *
1#
#420
0#
#430
b10000000000000001 "
b10000000000000001 (
b10000000000000001 ,
b10000000000000001 .
b111111111111111111111111 !
b111111111111111111111111 '
b1111111111111111111111111 )
b10011001 *
1#
#440
0#
#450
b100000000000000010000000000000001 "
b100000000000000010000000000000001 (
b100000000000000010000000000000001 ,
b100000000000000010000000000000001 .
b0 !
b0 '
b10011001 *
b1 )
1#
#460
0#
#470
b1000000000000000100000000000000010000000000000001 "
b1000000000000000100000000000000010000000000000001 (
b1000000000000000100000000000000010000000000000001 ,
b1000000000000000100000000000000010000000000000001 .
b101 !
b101 '
b10011001 *
b1011 )
1#
#480
0#
#490
b10000000000000001000000000000000100000000000000010000000000000001 "
b10000000000000001000000000000000100000000000000010000000000000001 (
b10000000000000001000000000000000100000000000000010000000000000001 ,
b10000000000000001000000000000000100000000000000010000000000000001 .
b110 !
b110 '
b10011001 *
b1100 )
1#
#500
0#
#510
b100000000000000010000000000000001000000000000000100000000000000010000000000000001 "
b100000000000000010000000000000001000000000000000100000000000000010000000000000001 (
b100000000000000010000000000000001000000000000000100000000000000010000000000000001 ,
b100000000000000010000000000000001000000000000000100000000000000010000000000000001 .
b111111111111111111110101 !
b111111111111111111110101 '
b10011001 *
b1111111111111111111101011 )
1#
#520
0#
