Firmware/counter_mod2/counter_mod2.v
///////////////////////////////////////////////////////////////////////////////
// $Author: BH $    $Date: 2018-11-04 $    $Revision: 1 $
//
// Module: counter_mod2.v
// Project: iCESDM (Sigma Delta Modulator for Lattice iCE40)
// Description: Arbitrary 2^n counter register.
//
// Change history:  2018-11-04 Created file.
//                  2018-11-11 Changed parameter name from N to WIDTH.
//                  2020-06-25 Made reset synchronous to be synthesizable on iCE40 hardware.
//                             Renamed inputs/outputs with i_/o_ prefix.
//                  2021-03-05 Added conditional compilation flag.
//
///////////////////////////////////////////////////////////////////////////////

`ifndef __COUNTER_MOD2_INCLUDE__
`define __COUNTER_MOD2_INCLUDE__
`endif

module counter_mod2(i_clk, i_en, i_rst, i_ld, i_up, i_data, o_data);
    parameter WIDTH = 4;
    parameter STEP = 1;
    input i_clk, i_en, i_rst, i_up, i_ld;
    input [WIDTH-1:0] i_data;
    output [WIDTH-1:0] o_data;
    reg [WIDTH-1:0] next;

    initial
    begin
        next = {WIDTH{1'b0}};
    end

    always @(posedge i_clk)
    begin
        if (i_en) begin
            if (i_rst)
                next <= {WIDTH{1'b0}};
            else if (i_ld)
                next <= i_data;
            else if (i_up)
                next <= next + STEP;
            else
                next <= next - STEP;
        end
    end
    assign o_data = next;
endmodule

Firmware/counter_mod2/counter_mod2_tb.v
///////////////////////////////////////////////////////////////////////////////
// $Author: BH $    $Date: 2018-11-05 $    $Revision: 0 $
//
// Module: counter_mod2_tb.v
// Project: iCESDM (Sigma Delta Modulator for Lattice iCE40)
// Description: Test bench for arbitrary 2^n counter register.
//
// Change history: 2018-11-05 Created file.
//
///////////////////////////////////////////////////////////////////////////////

`timescale 1ns/1ns
`include "counter_mod2.v"
module counter_mod2_tb();
 
reg clk, rst, up, ld, en;
reg [7:0] din;
wire [7:0] dout;
 
counter_mod2 #(
    .WIDTH(8)
) DUT (
    .i_clk(clk),
    .i_en(en),
    .i_rst(rst),
    .i_up(up),
    .i_ld(ld),
    .i_data(din),
    .o_data(dout)
);
 
always
#10 clk = ~clk;
 
initial
begin
    clk = 0;
    en = 1'b1;
    rst = 0;
    din = 8'hFE;
    up = 1'b0;
    ld = 1'b0;
    #50 ld = 1'b1;
    #60 ld = 0;
    #20 up = 1'b1;
    #15 en = 0;
    #35 rst = 1'b1;
end
 
initial 
begin
    #400 $stop;
end
 
initial
begin
    $dumpfile("out.vcd");
    $dumpvars(0,DUT);
end
 
initial
$monitor($stime,, rst,, clk,,, din,, ld,, dout);
 
endmodule

Firmware/counter_mod2/out.vcd
$date
	Fri Jun 26 16:00:22 2020
$end
$version
	Icarus Verilog
$end
$timescale
	1ns
$end
$scope module counter_mod2_tb $end
$scope module DUT $end
$var wire 1 ! i_clk $end
$var wire 8 " i_data [7:0] $end
$var wire 1 # i_en $end
$var wire 1 $ i_ld $end
$var wire 1 % i_rst $end
$var wire 1 & i_up $end
$var wire 8 ' o_data [7:0] $end
$var reg 8 ( next [7:0] $end
$upscope $end
$upscope $end
$enddefinitions $end
#0
$dumpvars
bx (
bx '
0&
0%
0$
1#
b11111110 "
0!
$end
#10
1!
#20
0!
#30
1!
#40
0!
#50
b11111110 '
b11111110 (
1!
1$
#60
0!
#70
1!
#80
0!
#90
1!
#100
0!
#110
b11111101 '
b11111101 (
1!
0$
#120
0!
#130
b11111110 '
b11111110 (
1!
1&
#140
0!
#150
b11111111 '
b11111111 (
1!
#160
0!
#170
b0 '
b0 (
1!
#180
0!
#190
b1 '
b1 (
1!
#200
0!
#210
b10 '
b10 (
1!
#220
0!
#230
b11 '
b11 (
1!
#240
0!
#250
b100 '
b100 (
1!
#260
0!
#270
b101 '
b101 (
1!
#280
0!
#290
b110 '
b110 (
1!
#295
0#
#300
0!
#310
1!
#320
0!
#330
1!
1%
