Firmware/rom_2ch/rom_2ch.v
///////////////////////////////////////////////////////////////////////////////
// $Author: BH $    $Date: 2020-07-10 $    $Revision: 0 $
//
// Module: rom_2ch.v
// Project: iCESDM (Sigma Delta Modulator for Lattice iCE40)
// Description: 2-channel read only memory.
//
// Change history:  2020-07-10 Created file.
//                  2021-03-02 Parameterized data loading path.
//                  2021-03-05 Added conditional compilation flag.
//
///////////////////////////////////////////////////////////////////////////////

`ifndef __ROM_2CH_INCLUDE__
`define __ROM_2CH_INCLUDE__

module rom_2ch(i_clk, i_en, i_addr_a, i_addr_b, o_data_a, o_data_b);
    parameter ADDR_WIDTH = 9;
    parameter DATA_WIDTH = 8;
    parameter LOAD_PATH = "";
    input i_clk, i_en;
    input [(ADDR_WIDTH-1):0] i_addr_a, i_addr_b;
    output reg [(DATA_WIDTH-1):0] o_data_a, o_data_b;
    reg [(DATA_WIDTH-1):0] mem [0:((1<<ADDR_WIDTH)-1)];

    initial if (LOAD_PATH) $readmemh(LOAD_PATH, mem);

    always @(posedge i_clk)
    begin
        if (i_en)
            o_data_a <= mem[i_addr_a];
            o_data_b <= mem[i_addr_b];
    end
endmodule

Firmware/sine_lut/sine_lut.v
///////////////////////////////////////////////////////////////////////////////
// $Author: BH $    $Date: 2020-04-15 $    $Revision: 1 $
//
// Module: sine_lut.v
// Project: iCESDM (Sigma Delta Modulator for Lattice iCE40)
// Description: Quarter-wave sin lookup table.
// See also: https://zipcpu.com/dsp/2017/08/26/quarterwave.html
//
// Change history:  2020-04-15 Created file.
//                  2021-03-05 Added conditional compilation flag.
//
///////////////////////////////////////////////////////////////////////////////

`ifndef __SINE_LUT_INCLUDE__
`define __SINE_LUT_INCLUDE__
`endif
`ifndef __ROM_2CH_INCLUDE__
`include "../rom_2ch/rom_2ch.v"
`endif

module sine_lut(i_clk, i_rst, i_en, i_phase, o_sin, o_cos);
    parameter I_WIDTH = 13;
    parameter O_WIDTH = 12;
    parameter LOAD_PATH = "";
    input i_clk, i_rst, i_en;
    input wire [(I_WIDTH-1):0] i_phase;
    output reg [(O_WIDTH-1):0] o_sin, o_cos;
    wire [(O_WIDTH-1):0] data_sin, data_cos;
    reg [(O_WIDTH-1):0] sin, cos;
    reg [(I_WIDTH-3):0] addr_sin, addr_cos;
    reg [1:0] negate_sin, negate_cos;

    rom_2ch #(
        .ADDR_WIDTH(I_WIDTH-2), // Divide by 4 due to sine wave symmetry.
        .DATA_WIDTH(O_WIDTH),
        .LOAD_PATH(LOAD_PATH)
    ) lut (
        .i_clk(i_clk),
        .i_en(i_en),
        .i_addr_a(addr_sin),
        .i_addr_b(addr_cos),
        .o_data_a(data_sin),
        .o_data_b(data_cos)
    );

    always @(posedge i_clk)
    begin
        if (i_rst)
        begin
            negate_sin = 2'b0;
            negate_cos = 2'b0;
            addr_sin = 0;
            addr_cos = 0;
            sin = 0;
            cos = 0;
        end
        else if (i_en)
        begin
            // Clock 1
            negate_sin[0] <= i_phase[(I_WIDTH-1)];
            negate_cos[0] <= i_phase[I_WIDTH-1] ^ i_phase[I_WIDTH-2];
            if (i_phase[(I_WIDTH-2)])
            begin
                addr_sin <= ~i_phase[(I_WIDTH-3):0];
                addr_cos <= i_phase[(I_WIDTH-3):0];
            end
            else
            begin
                addr_sin <= i_phase[(I_WIDTH-3):0];
                addr_cos <= ~i_phase[(I_WIDTH-3):0];
            end
            // Clock 2
            sin <= data_sin;
            cos <= data_cos;
            negate_sin[1] <= negate_sin[0];
            negate_cos[1] <= negate_cos[0];
            // Clock 3
            if (negate_sin[1])
                o_sin <= ~sin;
            else
                o_sin <= sin;
            if (negate_cos[1])
                o_cos <= ~cos;
            else
                o_cos <= cos;
        end
    end
endmodule

Firmware/sine_lut/sine_lut_tb.v
///////////////////////////////////////////////////////////////////////////////
// $Author: BH $    $Date: 2020-04-17 $    $Revision: 0 $
//
// Module: sine_lut_tb.v
// Project: iCESDM (Sigma Delta Modulator for Lattice iCE40)
// Description: Test bench for sine wave LUT.
//
// Change history: 2020-04-17 Created file.
//
///////////////////////////////////////////////////////////////////////////////

`timescale 1ns/1ns
`include "sine_lut.v"
module sine_lut_tb();

reg clk, rst, en;
reg [7:0] phase;
wire [7:0] dout_sin, dout_cos;

sine_lut #(
    .I_WIDTH(8),
    .O_WIDTH(8)
) DUT (
    .i_clk(clk),
    .i_rst(rst),
    .i_en(en),
    .i_phase(phase),
    .o_sin(dout_sin),
    .o_cos(dout_cos)
);

always
#10 clk = ~clk;

always 
#40 phase = phase + 8'b1;

initial
begin
    clk = 0;
    en = 1;
    rst = 0;
    phase = 8'd0;
end

initial 
begin
    #10000 $stop;
end

initial
begin
    $dumpfile("out.vcd");
    $dumpvars(0,DUT);
end
 
initial
$monitor($stime,, rst,, clk,, phase,, dout_sin,, dout_cos);

endmodule

Firmware/sine_lut/out.vcd
$date
	Fri Jul 10 13:05:54 2020
$end
$version
	Icarus Verilog
$end
$timescale
	1ns
$end
$scope module sine_lut_tb $end
$scope module DUT $end
$var wire 1 ! i_clk $end
$var wire 1 " i_en $end
$var wire 8 # i_phase [7:0] $end
$var wire 1 $ i_rst $end
$var wire 8 % data_sin [7:0] $end
$var wire 8 & data_cos [7:0] $end
$var reg 6 ' addr_cos [5:0] $end
$var reg 6 ( addr_sin [5:0] $end
$var reg 8 ) cos [7:0] $end
$var reg 2 * negate_cos [1:0] $end
$var reg 2 + negate_sin [1:0] $end
$var reg 8 , o_cos [7:0] $end
$var reg 8 - o_sin [7:0] $end
$var reg 8 . sin [7:0] $end
$scope module lut $end
$var wire 6 / i_addr_a [5:0] $end
$var wire 6 0 i_addr_b [5:0] $end
$var wire 1 ! i_clk $end
$var wire 1 " i_en $end
$var reg 8 1 o_data_a [7:0] $end
$var reg 8 2 o_data_b [7:0] $end
$upscope $end
$upscope $end
$upscope $end
$enddefinitions $end
#0
$dumpvars
bx 2
bx 1
bx 0
bx /
bx .
bx -
bx ,
bx +
bx *
bx )
bx (
bx '
bx &
bx %
0$
b0 #
1"
0!
$end
#10
b111111 '
b111111 0
b0 (
b0 /
bx0 *
bx0 +
1!
#20
0!
#30
b0 *
b0 +
b1111111 &
b1111111 2
b11 %
b11 1
1!
#40
0!
b1 #
#50
b1111111 )
b11 .
b111110 '
b111110 0
b1 (
b1 /
1!
#60
0!
#70
b1111111 ,
b11 -
b1111110 &
b1111110 2
b110 %
b110 1
1!
#80
0!
b10 #
#90
b1111110 )
b110 .
b111101 '
b111101 0
b10 (
b10 /
1!
#100
0!
#110
b1111110 ,
b110 -
b1001 %
b1001 1
1!
#120
0!
b11 #
#130
b1001 .
b111100 '
b111100 0
b11 (
b11 /
1!
#140
0!
#150
b1001 -
b1100 %
b1100 1
1!
#160
0!
b100 #
#170
b1100 .
b111011 '
b111011 0
b100 (
b100 /
1!
#180
0!
#190
b1100 -
b1111 %
b1111 1
1!
#200
0!
b101 #
#210
b1111 .
b111010 '
b111010 0
b101 (
b101 /
1!
#220
0!
#230
b1111 -
b10010 %
b10010 1
1!
#240
0!
b110 #
#250
b10010 .
b111001 '
b111001 0
b110 (
b110 /
1!
#260
0!
#270
b10010 -
b1111101 &
b1111101 2
b10101 %
b10101 1
1!
#280
0!
b111 #
#290
b1111101 )
b10101 .
b111000 '
b111000 0
b111 (
b111 /
1!
#300
0!
#310
b1111101 ,
b10101 -
b11000 %
b11000 1
1!
#320
0!
b1000 #
#330
b11000 .
b110111 '
b110111 0
b1000 (
b1000 /
1!
#340
0!
#350
b11000 -
b1111100 &
b1111100 2
b11011 %
b11011 1
1!
#360
0!
b1001 #
#370
b1111100 )
b11011 .
b110110 '
b110110 0
b1001 (
b1001 /
1!
#380
0!
#390
b1111100 ,
b11011 -
b1111011 &
b1111011 2
b11110 %
b11110 1
1!
#400
0!
b1010 #
#410
b1111011 )
b11110 .
b110101 '
b110101 0
b1010 (
b1010 /
1!
#420
0!
#430
b1111011 ,
b11110 -
b100001 %
b100001 1
1!
#440
0!
b1011 #
#450
b100001 .
b110100 '
b110100 0
b1011 (
b1011 /
1!
#460
0!
#470
b100001 -
b1111010 &
b1111010 2
b100100 %
b100100 1
1!
#480
0!
b1100 #
#490
b1111010 )
b100100 .
b110011 '
b110011 0
b1100 (
b1100 /
1!
#500
0!
#510
b1111010 ,
b100100 -
b1111001 &
b1111001 2
b100111 %
b100111 1
1!
#520
0!
b1101 #
#530
b1111001 )
b100111 .
b110010 '
b110010 0
b1101 (
b1101 /
1!
#540
0!
#550
b1111001 ,
b100111 -
b1111000 &
b1111000 2
b101010 %
b101010 1
1!
#560
0!
b1110 #
#570
b1111000 )
b101010 .
b110001 '
b110001 0
b1110 (
b1110 /
1!
#580
0!
#590
b1111000 ,
b101010 -
b1110111 &
b1110111 2
b101101 %
b101101 1
1!
#600
0!
b1111 #
#610
b1110111 )
b101101 .
b110000 '
b110000 0
b1111 (
b1111 /
1!
#620
0!
#630
b1110111 ,
b101101 -
b1110110 &
b1110110 2
b110000 %
b110000 1
1!
#640
0!
b10000 #
#650
b1110110 )
b110000 .
b101111 '
b101111 0
b10000 (
b10000 /
1!
#660
0!
#670
b1110110 ,
b110000 -
b1110101 &
b1110101 2
b110011 %
b110011 1
1!
#680
0!
b10001 #
#690
b1110101 )
b110011 .
b101110 '
b101110 0
b10001 (
b10001 /
1!
#700
0!
#710
b1110101 ,
b110011 -
b1110100 &
b1110100 2
b110110 %
b110110 1
1!
#720
0!
b10010 #
#730
b1110100 )
b110110 .
b101101 '
b101101 0
b10010 (
b10010 /
1!
#740
0!
#750
b1110100 ,
b110110 -
b1110010 &
b1110010 2
b111001 %
b111001 1
1!
#760
0!
b10011 #
#770
b1110010 )
b111001 .
b101100 '
b101100 0
b10011 (
b10011 /
1!
#780
0!
#790
b1110010 ,
b111001 -
b1110001 &
b1110001 2
b111011 %
b111011 1
1!
#800
0!
b10100 #
#810
b1110001 )
b111011 .
b101011 '
b101011 0
b10100 (
b10100 /
1!
#820
0!
#830
b1110001 ,
b111011 -
b1110000 &
b1110000 2
b111110 %
b111110 1
1!
#840
0!
b10101 #
#850
b1110000 )
b111110 .
b101010 '
b101010 0
b10101 (
b10101 /
1!
#860
0!
#870
b1110000 ,
b111110 -
b1101110 &
b1101110 2
b1000001 %
b1000001 1
1!
#880
0!
b10110 #
#890
b1101110 )
b1000001 .
b101001 '
b101001 0
b10110 (
b10110 /
1!
#900
0!
#910
b1101110 ,
b1000001 -
b1101100 &
b1101100 2
b1000011 %
b1000011 1
1!
#920
0!
b10111 #
#930
b1101100 )
b1000011 .
b101000 '
b101000 0
b10111 (
b10111 /
1!
#940
0!
#950
b1101100 ,
b1000011 -
b1101011 &
b1101011 2
b1000110 %
b1000110 1
1!
#960
0!
b11000 #
#970
b1101011 )
b1000110 .
b100111 '
b100111 0
b11000 (
b11000 /
1!
#980
0!
#990
b1101011 ,
b1000110 -
b1101001 &
b1101001 2
b1001001 %
b1001001 1
1!
#1000
0!
b11001 #
#1010
b1101001 )
b1001001 .
b100110 '
b100110 0
b11001 (
b11001 /
1!
#1020
0!
#1030
b1101001 ,
b1001001 -
b1100111 &
b1100111 2
b1001011 %
b1001011 1
1!
#1040
0!
b11010 #
#1050
b1100111 )
b1001011 .
b100101 '
b100101 0
b11010 (
b11010 /
1!
#1060
0!
#1070
b1100111 ,
b1001011 -
b1100110 &
b1100110 2
b1001110 %
b1001110 1
1!
#1080
0!
b11011 #
#1090
b1100110 )
b1001110 .
b100100 '
b100100 0
b11011 (
b11011 /
1!
#1100
0!
#1110
b1100110 ,
b1001110 -
b1100100 &
b1100100 2
b1010000 %
b1010000 1
1!
#1120
0!
b11100 #
#1130
b1100100 )
b1010000 .
b100011 '
b100011 0
b11100 (
b11100 /
1!
#1140
0!
#1150
b1100100 ,
b1010000 -
b1100010 &
b1100010 2
b1010010 %
b1010010 1
1!
#1160
0!
b11101 #
#1170
b1100010 )
b1010010 .
b100010 '
b100010 0
b11101 (
b11101 /
1!
#1180
0!
#1190
b1100010 ,
b1010010 -
b1100000 &
b1100000 2
b1010101 %
b1010101 1
1!
#1200
0!
b11110 #
#1210
b1100000 )
b1010101 .
b100001 '
b100001 0
b11110 (
b11110 /
1!
#1220
0!
#1230
b1100000 ,
b1010101 -
b1011110 &
b1011110 2
b1010111 %
b1010111 1
1!
#1240
0!
b11111 #
#1250
b1011110 )
b1010111 .
b100000 '
b100000 0
b11111 (
b11111 /
1!
#1260
0!
#1270
b1011110 ,
b1010111 -
b1011011 &
b1011011 2
b1011001 %
b1011001 1
1!
#1280
0!
b100000 #
#1290
b1011011 )
b1011001 .
b11111 '
b11111 0
b100000 (
b100000 /
1!
#1300
0!
#1310
b1011011 ,
b1011001 -
b1011001 &
b1011001 2
b1011011 %
b1011011 1
1!
#1320
0!
b100001 #
#1330
b1011001 )
b1011011 .
b11110 '
b11110 0
b100001 (
b100001 /
1!
#1340
0!
#1350
b1011001 ,
b1011011 -
b1010111 &
b1010111 2
b1011110 %
b1011110 1
1!
#1360
0!
b100010 #
#1370
b1010111 )
b1011110 .
b11101 '
b11101 0
b100010 (
b100010 /
1!
#1380
0!
#1390
b1010111 ,
b1011110 -
b1010101 &
b1010101 2
b1100000 %
b1100000 1
1!
#1400
0!
b100011 #
#1410
b1010101 )
b1100000 .
b11100 '
b11100 0
b100011 (
b100011 /
1!
#1420
0!
#1430
b1010101 ,
b1100000 -
b1010010 &
b1010010 2
b1100010 %
b1100010 1
1!
#1440
0!
b100100 #
#1450
b1010010 )
b1100010 .
b11011 '
b11011 0
b100100 (
b100100 /
1!
#1460
0!
#1470
b1010010 ,
b1100010 -
b1010000 &
b1010000 2
b1100100 %
b1100100 1
1!
#1480
0!
b100101 #
#1490
b1010000 )
b1100100 .
b11010 '
b11010 0
b100101 (
b100101 /
1!
#1500
0!
#1510
b1010000 ,
b1100100 -
b1001110 &
b1001110 2
b1100110 %
b1100110 1
1!
#1520
0!
b100110 #
#1530
b1001110 )
b1100110 .
b11001 '
b11001 0
b100110 (
b100110 /
1!
#1540
0!
#1550
b1001110 ,
b1100110 -
b1001011 &
b1001011 2
b1100111 %
b1100111 1
1!
#1560
0!
b100111 #
#1570
b1001011 )
b1100111 .
b11000 '
b11000 0
b100111 (
b100111 /
1!
#1580
0!
#1590
b1001011 ,
b1100111 -
b1001001 &
b1001001 2
b1101001 %
b1101001 1
1!
#1600
0!
b101000 #
#1610
b1001001 )
b1101001 .
b10111 '
b10111 0
b101000 (
b101000 /
1!
#1620
0!
#1630
b1001001 ,
b1101001 -
b1000110 &
b1000110 2
b1101011 %
b1101011 1
1!
#1640
0!
b101001 #
#1650
b1000110 )
b1101011 .
b10110 '
b10110 0
b101001 (
b101001 /
1!
#1660
0!
#1670
b1000110 ,
b1101011 -
b1000011 &
b1000011 2
b1101100 %
b1101100 1
1!
#1680
0!
b101010 #
#1690
b1000011 )
b1101100 .
b10101 '
b10101 0
b101010 (
b101010 /
1!
#1700
0!
#1710
b1000011 ,
b1101100 -
b1000001 &
b1000001 2
b1101110 %
b1101110 1
1!
#1720
0!
b101011 #
#1730
b1000001 )
b1101110 .
b10100 '
b10100 0
b101011 (
b101011 /
1!
#1740
0!
#1750
b1000001 ,
b1101110 -
b111110 &
b111110 2
b1110000 %
b1110000 1
1!
#1760
0!
b101100 #
#1770
b111110 )
b1110000 .
b10011 '
b10011 0
b101100 (
b101100 /
1!
#1780
0!
#1790
b111110 ,
b1110000 -
b111011 &
b111011 2
b1110001 %
b1110001 1
1!
#1800
0!
b101101 #
#1810
b111011 )
b1110001 .
b10010 '
b10010 0
b101101 (
b101101 /
1!
#1820
0!
#1830
b111011 ,
b1110001 -
b111001 &
b111001 2
b1110010 %
b1110010 1
1!
#1840
0!
b101110 #
#1850
b111001 )
b1110010 .
b10001 '
b10001 0
b101110 (
b101110 /
1!
#1860
0!
#1870
b111001 ,
b1110010 -
b110110 &
b110110 2
b1110100 %
b1110100 1
1!
#1880
0!
b101111 #
#1890
b110110 )
b1110100 .
b10000 '
b10000 0
b101111 (
b101111 /
1!
#1900
0!
#1910
b110110 ,
b1110100 -
b110011 &
b110011 2
b1110101 %
b1110101 1
1!
#1920
0!
b110000 #
#1930
b110011 )
b1110101 .
b1111 '
b1111 0
b110000 (
b110000 /
1!
#1940
0!
#1950
b110011 ,
b1110101 -
b110000 &
b110000 2
b1110110 %
b1110110 1
1!
#1960
0!
b110001 #
#1970
b110000 )
b1110110 .
b1110 '
b1110 0
b110001 (
b110001 /
1!
#1980
0!
#1990
b110000 ,
b1110110 -
b101101 &
b101101 2
b1110111 %
b1110111 1
1!
#2000
0!
b110010 #
#2010
b101101 )
b1110111 .
b1101 '
b1101 0
b110010 (
b110010 /
1!
#2020
0!
#2030
b101101 ,
b1110111 -
b101010 &
b101010 2
b1111000 %
b1111000 1
1!
#2040
0!
b110011 #
#2050
b101010 )
b1111000 .
b1100 '
b1100 0
b110011 (
b110011 /
1!
#2060
0!
#2070
b101010 ,
b1111000 -
b100111 &
b100111 2
b1111001 %
b1111001 1
1!
#2080
0!
b110100 #
#2090
b100111 )
b1111001 .
b1011 '
b1011 0
b110100 (
b110100 /
1!
#2100
0!
#2110
b100111 ,
b1111001 -
b100100 &
b100100 2
b1111010 %
b1111010 1
1!
#2120
0!
b110101 #
#2130
b100100 )
b1111010 .
b1010 '
b1010 0
b110101 (
b110101 /
1!
#2140
0!
#2150
b100100 ,
b1111010 -
b100001 &
b100001 2
b1111011 %
b1111011 1
1!
#2160
0!
b110110 #
#2170
b100001 )
b1111011 .
b1001 '
b1001 0
b110110 (
b110110 /
1!
#2180
0!
#2190
b100001 ,
b1111011 -
b11110 &
b11110 2
1!
#2200
0!
b110111 #
#2210
b11110 )
b1000 '
b1000 0
b110111 (
b110111 /
1!
#2220
0!
#2230
b11110 ,
b11011 &
b11011 2
b1111100 %
b1111100 1
1!
#2240
0!
b111000 #
#2250
b11011 )
b1111100 .
b111 '
b111 0
b111000 (
b111000 /
1!
#2260
0!
#2270
b11011 ,
b1111100 -
b11000 &
b11000 2
b1111101 %
b1111101 1
1!
#2280
0!
b111001 #
#2290
b11000 )
b1111101 .
b110 '
b110 0
b111001 (
b111001 /
1!
#2300
0!
#2310
b11000 ,
b1111101 -
b10101 &
b10101 2
1!
#2320
0!
b111010 #
#2330
b10101 )
b101 '
b101 0
b111010 (
b111010 /
1!
#2340
0!
#2350
b10101 ,
b10010 &
b10010 2
b1111110 %
b1111110 1
1!
#2360
0!
b111011 #
#2370
b10010 )
b1111110 .
b100 '
b100 0
b111011 (
b111011 /
1!
#2380
0!
#2390
b10010 ,
b1111110 -
b1111 &
b1111 2
1!
#2400
0!
b111100 #
#2410
b1111 )
b11 '
b11 0
b111100 (
b111100 /
1!
#2420
0!
#2430
b1111 ,
b1100 &
b1100 2
1!
#2440
0!
b111101 #
#2450
b1100 )
b10 '
b10 0
b111101 (
b111101 /
1!
#2460
0!
#2470
b1100 ,
b1001 &
b1001 2
1!
#2480
0!
b111110 #
#2490
b1001 )
b1 '
b1 0
b111110 (
b111110 /
1!
#2500
0!
#2510
b1001 ,
b110 &
b110 2
1!
#2520
0!
b111111 #
#2530
b110 )
b0 '
b0 0
b111111 (
b111111 /
1!
#2540
0!
#2550
b110 ,
b11 &
b11 2
b1111111 %
b1111111 1
1!
#2560
0!
b1000000 #
#2570
b11 )
b1111111 .
b1 *
1!
#2580
0!
#2590
b11 ,
b1111111 -
b11 *
1!
#2600
0!
b1000001 #
#2610
b11111100 ,
b1 '
b1 0
b111110 (
b111110 /
1!
#2620
0!
#2630
b110 &
b110 2
b1111110 %
b1111110 1
1!
#2640
0!
b1000010 #
#2650
b110 )
b1111110 .
b10 '
b10 0
b111101 (
b111101 /
1!
#2660
0!
#2670
b11111001 ,
b1111110 -
b1001 &
b1001 2
1!
#2680
0!
b1000011 #
#2690
b1001 )
b11 '
b11 0
b111100 (
b111100 /
1!
#2700
0!
#2710
b11110110 ,
b1100 &
b1100 2
1!
#2720
0!
b1000100 #
#2730
b1100 )
b100 '
b100 0
b111011 (
b111011 /
1!
#2740
0!
#2750
b11110011 ,
b1111 &
b1111 2
1!
#2760
0!
b1000101 #
#2770
b1111 )
b101 '
b101 0
b111010 (
b111010 /
1!
#2780
0!
#2790
b11110000 ,
b10010 &
b10010 2
1!
#2800
0!
b1000110 #
#2810
b10010 )
b110 '
b110 0
b111001 (
b111001 /
1!
#2820
0!
#2830
b11101101 ,
b10101 &
b10101 2
b1111101 %
b1111101 1
1!
#2840
0!
b1000111 #
#2850
b10101 )
b1111101 .
b111 '
b111 0
b111000 (
b111000 /
1!
#2860
0!
#2870
b11101010 ,
b1111101 -
b11000 &
b11000 2
1!
#2880
0!
b1001000 #
#2890
b11000 )
b1000 '
b1000 0
b110111 (
b110111 /
1!
#2900
0!
#2910
b11100111 ,
b11011 &
b11011 2
b1111100 %
b1111100 1
1!
#2920
0!
b1001001 #
#2930
b11011 )
b1111100 .
b1001 '
b1001 0
b110110 (
b110110 /
1!
#2940
0!
#2950
b11100100 ,
b1111100 -
b11110 &
b11110 2
b1111011 %
b1111011 1
1!
#2960
0!
b1001010 #
#2970
b11110 )
b1111011 .
b1010 '
b1010 0
b110101 (
b110101 /
1!
#2980
0!
#2990
b11100001 ,
b1111011 -
b100001 &
b100001 2
1!
#3000
0!
b1001011 #
#3010
b100001 )
b1011 '
b1011 0
b110100 (
b110100 /
1!
#3020
0!
#3030
b11011110 ,
b100100 &
b100100 2
b1111010 %
b1111010 1
1!
#3040
0!
b1001100 #
#3050
b100100 )
b1111010 .
b1100 '
b1100 0
b110011 (
b110011 /
1!
#3060
0!
#3070
b11011011 ,
b1111010 -
b100111 &
b100111 2
b1111001 %
b1111001 1
1!
#3080
0!
b1001101 #
#3090
b100111 )
b1111001 .
b1101 '
b1101 0
b110010 (
b110010 /
1!
#3100
0!
#3110
b11011000 ,
b1111001 -
b101010 &
b101010 2
b1111000 %
b1111000 1
1!
#3120
0!
b1001110 #
#3130
b101010 )
b1111000 .
b1110 '
b1110 0
b110001 (
b110001 /
1!
#3140
0!
#3150
b11010101 ,
b1111000 -
b101101 &
b101101 2
b1110111 %
b1110111 1
1!
#3160
0!
b1001111 #
#3170
b101101 )
b1110111 .
b1111 '
b1111 0
b110000 (
b110000 /
1!
#3180
0!
#3190
b11010010 ,
b1110111 -
b110000 &
b110000 2
b1110110 %
b1110110 1
1!
#3200
0!
b1010000 #
#3210
b110000 )
b1110110 .
b10000 '
b10000 0
b101111 (
b101111 /
1!
#3220
0!
#3230
b11001111 ,
b1110110 -
b110011 &
b110011 2
b1110101 %
b1110101 1
1!
#3240
0!
b1010001 #
#3250
b110011 )
b1110101 .
b10001 '
b10001 0
b101110 (
b101110 /
1!
#3260
0!
#3270
b11001100 ,
b1110101 -
b110110 &
b110110 2
b1110100 %
b1110100 1
1!
#3280
0!
b1010010 #
#3290
b110110 )
b1110100 .
b10010 '
b10010 0
b101101 (
b101101 /
1!
#3300
0!
#3310
b11001001 ,
b1110100 -
b111001 &
b111001 2
b1110010 %
b1110010 1
1!
#3320
0!
b1010011 #
#3330
b111001 )
b1110010 .
b10011 '
b10011 0
b101100 (
b101100 /
1!
#3340
0!
#3350
b11000110 ,
b1110010 -
b111011 &
b111011 2
b1110001 %
b1110001 1
1!
#3360
0!
b1010100 #
#3370
b111011 )
b1110001 .
b10100 '
b10100 0
b101011 (
b101011 /
1!
#3380
0!
#3390
b11000100 ,
b1110001 -
b111110 &
b111110 2
b1110000 %
b1110000 1
1!
#3400
0!
b1010101 #
#3410
b111110 )
b1110000 .
b10101 '
b10101 0
b101010 (
b101010 /
1!
#3420
0!
#3430
b11000001 ,
b1110000 -
b1000001 &
b1000001 2
b1101110 %
b1101110 1
1!
#3440
0!
b1010110 #
#3450
b1000001 )
b1101110 .
b10110 '
b10110 0
b101001 (
b101001 /
1!
#3460
0!
#3470
b10111110 ,
b1101110 -
b1000011 &
b1000011 2
b1101100 %
b1101100 1
1!
#3480
0!
b1010111 #
#3490
b1000011 )
b1101100 .
b10111 '
b10111 0
b101000 (
b101000 /
1!
#3500
0!
#3510
b10111100 ,
b1101100 -
b1000110 &
b1000110 2
b1101011 %
b1101011 1
1!
#3520
0!
b1011000 #
#3530
b1000110 )
b1101011 .
b11000 '
b11000 0
b100111 (
b100111 /
1!
#3540
0!
#3550
b10111001 ,
b1101011 -
b1001001 &
b1001001 2
b1101001 %
b1101001 1
1!
#3560
0!
b1011001 #
#3570
b1001001 )
b1101001 .
b11001 '
b11001 0
b100110 (
b100110 /
1!
#3580
0!
#3590
b10110110 ,
b1101001 -
b1001011 &
b1001011 2
b1100111 %
b1100111 1
1!
#3600
0!
b1011010 #
#3610
b1001011 )
b1100111 .
b11010 '
b11010 0
b100101 (
b100101 /
1!
#3620
0!
#3630
b10110100 ,
b1100111 -
b1001110 &
b1001110 2
b1100110 %
b1100110 1
1!
#3640
0!
b1011011 #
#3650
b1001110 )
b1100110 .
b11011 '
b11011 0
b100100 (
b100100 /
1!
#3660
0!
#3670
b10110001 ,
b1100110 -
b1010000 &
b1010000 2
b1100100 %
b1100100 1
1!
#3680
0!
b1011100 #
#3690
b1010000 )
b1100100 .
b11100 '
b11100 0
b100011 (
b100011 /
1!
#3700
0!
#3710
b10101111 ,
b1100100 -
b1010010 &
b1010010 2
b1100010 %
b1100010 1
1!
#3720
0!
b1011101 #
#3730
b1010010 )
b1100010 .
b11101 '
b11101 0
b100010 (
b100010 /
1!
#3740
0!
#3750
b10101101 ,
b1100010 -
b1010101 &
b1010101 2
b1100000 %
b1100000 1
1!
#3760
0!
b1011110 #
#3770
b1010101 )
b1100000 .
b11110 '
b11110 0
b100001 (
b100001 /
1!
#3780
0!
#3790
b10101010 ,
b1100000 -
b1010111 &
b1010111 2
b1011110 %
b1011110 1
1!
#3800
0!
b1011111 #
#3810
b1010111 )
b1011110 .
b11111 '
b11111 0
b100000 (
b100000 /
1!
#3820
0!
#3830
b10101000 ,
b1011110 -
b1011001 &
b1011001 2
b1011011 %
b1011011 1
1!
#3840
0!
b1100000 #
#3850
b1011001 )
b1011011 .
b100000 '
b100000 0
b11111 (
b11111 /
1!
#3860
0!
#3870
b10100110 ,
b1011011 -
b1011011 &
b1011011 2
b1011001 %
b1011001 1
1!
#3880
0!
b1100001 #
#3890
b1011011 )
b1011001 .
b100001 '
b100001 0
b11110 (
b11110 /
1!
#3900
0!
#3910
b10100100 ,
b1011001 -
b1011110 &
b1011110 2
b1010111 %
b1010111 1
1!
#3920
0!
b1100010 #
#3930
b1011110 )
b1010111 .
b100010 '
b100010 0
b11101 (
b11101 /
1!
#3940
0!
#3950
b10100001 ,
b1010111 -
b1100000 &
b1100000 2
b1010101 %
b1010101 1
1!
#3960
0!
b1100011 #
#3970
b1100000 )
b1010101 .
b100011 '
b100011 0
b11100 (
b11100 /
1!
#3980
0!
#3990
b10011111 ,
b1010101 -
b1100010 &
b1100010 2
b1010010 %
b1010010 1
1!
#4000
0!
b1100100 #
#4010
b1100010 )
b1010010 .
b100100 '
b100100 0
b11011 (
b11011 /
1!
#4020
0!
#4030
b10011101 ,
b1010010 -
b1100100 &
b1100100 2
b1010000 %
b1010000 1
1!
#4040
0!
b1100101 #
#4050
b1100100 )
b1010000 .
b100101 '
b100101 0
b11010 (
b11010 /
1!
#4060
0!
#4070
b10011011 ,
b1010000 -
b1100110 &
b1100110 2
b1001110 %
b1001110 1
1!
#4080
0!
b1100110 #
#4090
b1100110 )
b1001110 .
b100110 '
b100110 0
b11001 (
b11001 /
1!
#4100
0!
#4110
b10011001 ,
b1001110 -
b1100111 &
b1100111 2
b1001011 %
b1001011 1
1!
#4120
0!
b1100111 #
#4130
b1100111 )
b1001011 .
b100111 '
b100111 0
b11000 (
b11000 /
1!
#4140
0!
#4150
b10011000 ,
b1001011 -
b1101001 &
b1101001 2
b1001001 %
b1001001 1
1!
#4160
0!
b1101000 #
#4170
b1101001 )
b1001001 .
b101000 '
b101000 0
b10111 (
b10111 /
1!
#4180
0!
#4190
b10010110 ,
b1001001 -
b1101011 &
b1101011 2
b1000110 %
b1000110 1
1!
#4200
0!
b1101001 #
#4210
b1101011 )
b1000110 .
b101001 '
b101001 0
b10110 (
b10110 /
1!
#4220
0!
#4230
b10010100 ,
b1000110 -
b1101100 &
b1101100 2
b1000011 %
b1000011 1
1!
#4240
0!
b1101010 #
#4250
b1101100 )
b1000011 .
b101010 '
b101010 0
b10101 (
b10101 /
1!
#4260
0!
#4270
b10010011 ,
b1000011 -
b1101110 &
b1101110 2
b1000001 %
b1000001 1
1!
#4280
0!
b1101011 #
#4290
b1101110 )
b1000001 .
b101011 '
b101011 0
b10100 (
b10100 /
1!
#4300
0!
#4310
b10010001 ,
b1000001 -
b1110000 &
b1110000 2
b111110 %
b111110 1
1!
#4320
0!
b1101100 #
#4330
b1110000 )
b111110 .
b101100 '
b101100 0
b10011 (
b10011 /
1!
#4340
0!
#4350
b10001111 ,
b111110 -
b1110001 &
b1110001 2
b111011 %
b111011 1
1!
#4360
0!
b1101101 #
#4370
b1110001 )
b111011 .
b101101 '
b101101 0
b10010 (
b10010 /
1!
#4380
0!
#4390
b10001110 ,
b111011 -
b1110010 &
b1110010 2
b111001 %
b111001 1
1!
#4400
0!
b1101110 #
#4410
b1110010 )
b111001 .
b101110 '
b101110 0
b10001 (
b10001 /
1!
#4420
0!
#4430
b10001101 ,
b111001 -
b1110100 &
b1110100 2
b110110 %
b110110 1
1!
#4440
0!
b1101111 #
#4450
b1110100 )
b110110 .
b101111 '
b101111 0
b10000 (
b10000 /
1!
#4460
0!
#4470
b10001011 ,
b110110 -
b1110101 &
b1110101 2
b110011 %
b110011 1
1!
#4480
0!
b1110000 #
