Firmware/counter_modn/counter_modn.v
///////////////////////////////////////////////////////////////////////////////
// $Author: BH $    $Date: 2020-06-26 $    $Revision: 0 $
//
// Module: counter_modn.v
// Project: iCESDM (Sigma Delta Modulator for Lattice iCE40)
// Description: Arbitrary counter register.
//
// Change history:  2020-06-26 Created file.
//                  2021-03-05 Added conditional compilation flag.
//
///////////////////////////////////////////////////////////////////////////////

`ifndef __COUNTER_MODN_INCLUDE__
`define __COUNTER_MODN_INCLUDE__
`endif

module counter_modn(i_clk, i_en, i_rst, i_ld, i_data, o_data);
    parameter WIDTH = 4;
    parameter N = 10;
    input i_clk, i_en, i_rst, i_ld;
    input [WIDTH-1:0] i_data;
    output [WIDTH-1:0] o_data;
    reg [WIDTH-1:0] next;

    initial
    begin
        next = {WIDTH{1'b0}};
    end

    always @(posedge i_clk)
    begin
        if (i_en) begin
            if (i_rst)
                next <= {WIDTH{1'b0}};
            else if (i_ld)
                next <= i_data;
            else if (next == N-1)
                next <= {WIDTH{1'b0}};
            else
                next <= next + 1'b1;
        end
    end
    assign o_data = next;
endmodule

Firmware/counter_modn/counter_modn_tb.v
///////////////////////////////////////////////////////////////////////////////
// $Author: BH $    $Date: 2018-11-05 $    $Revision: 0 $
//
// Module: counter_modn_tb.v
// Project: iCESDM (Sigma Delta Modulator for Lattice iCE40)
// Description: Test bench for arbitrary counter register.
//
// Change history: 2020-06-26 Created file.
//
///////////////////////////////////////////////////////////////////////////////

`timescale 1ns/1ns
`include "counter_modn.v"
module counter_modn_tb();
 
reg clk, rst, ld, en;
reg [7:0] din;
wire [7:0] dout;
 
counter_modn #(
    .WIDTH(8),
    .N(21)
) DUT (
    .i_clk(clk),
    .i_en(en),
    .i_rst(rst),
    .i_ld(ld),
    .i_data(din),
    .o_data(dout)
);
 
always
#10 clk = ~clk;
 
initial
begin
    clk = 0;
    en = 1'b1;
    rst = 0;
    din = 8'b0;
    ld = 1'b0;
    #50 ld = 1'b1;
    #60 ld = 0;
    #1005 en = 0;
    #35 rst = 1'b1;
end
 
initial 
begin
    #1200 $stop;
end
 
initial
begin
    $dumpfile("out.vcd");
    $dumpvars(0,DUT);
end
 
initial
$monitor($stime,, rst,, clk,,, din,, ld,, dout);
 
endmodule

Firmware/counter_modn/out.vcd
$date
	Fri Jun 26 16:16:17 2020
$end
$version
	Icarus Verilog
$end
$timescale
	1ns
$end
$scope module counter_modn_tb $end
$scope module DUT $end
$var wire 1 ! i_clk $end
$var wire 8 " i_data [7:0] $end
$var wire 1 # i_en $end
$var wire 1 $ i_ld $end
$var wire 1 % i_rst $end
$var wire 8 & o_data [7:0] $end
$var reg 8 ' next [7:0] $end
$upscope $end
$upscope $end
$enddefinitions $end
#0
$dumpvars
bx '
bx &
0%
0$
1#
b0 "
0!
$end
#10
1!
#20
0!
#30
1!
#40
0!
#50
b0 &
b0 '
1!
1$
#60
0!
#70
1!
#80
0!
#90
1!
#100
0!
#110
b1 &
b1 '
1!
0$
#120
0!
#130
b10 &
b10 '
1!
#140
0!
#150
b11 &
b11 '
1!
#160
0!
#170
b100 &
b100 '
1!
#180
0!
#190
b101 &
b101 '
1!
#200
0!
#210
b110 &
b110 '
1!
#220
0!
#230
b111 &
b111 '
1!
#240
0!
#250
b1000 &
b1000 '
1!
#260
0!
#270
b1001 &
b1001 '
1!
#280
0!
#290
b1010 &
b1010 '
1!
#300
0!
#310
b1011 &
b1011 '
1!
#320
0!
#330
b1100 &
b1100 '
1!
#340
0!
#350
b1101 &
b1101 '
1!
#360
0!
#370
b1110 &
b1110 '
1!
#380
0!
#390
b1111 &
b1111 '
1!
#400
0!
#410
b10000 &
b10000 '
1!
#420
0!
#430
b10001 &
b10001 '
1!
#440
0!
#450
b10010 &
b10010 '
1!
#460
0!
#470
b10011 &
b10011 '
1!
#480
0!
#490
b10100 &
b10100 '
1!
#500
0!
#510
b0 &
b0 '
1!
#520
0!
#530
b1 &
b1 '
1!
#540
0!
#550
b10 &
b10 '
1!
#560
0!
#570
b11 &
b11 '
1!
#580
0!
#590
b100 &
b100 '
1!
#600
0!
#610
b101 &
b101 '
1!
#620
0!
#630
b110 &
b110 '
1!
#640
0!
#650
b111 &
b111 '
1!
#660
0!
#670
b1000 &
b1000 '
1!
#680
0!
#690
b1001 &
b1001 '
1!
#700
0!
#710
b1010 &
b1010 '
1!
#720
0!
#730
b1011 &
b1011 '
1!
#740
0!
#750
b1100 &
b1100 '
1!
#760
0!
#770
b1101 &
b1101 '
1!
#780
0!
#790
b1110 &
b1110 '
1!
#800
0!
#810
b1111 &
b1111 '
1!
#820
0!
#830
b10000 &
b10000 '
1!
#840
0!
#850
b10001 &
b10001 '
1!
#860
0!
#870
b10010 &
b10010 '
1!
#880
0!
#890
b10011 &
b10011 '
1!
#900
0!
#910
b10100 &
b10100 '
1!
#920
0!
#930
b0 &
b0 '
1!
#940
0!
#950
b1 &
b1 '
1!
#960
0!
#970
b10 &
b10 '
1!
#980
0!
#990
b11 &
b11 '
1!
#1000
0!
#1010
b100 &
b100 '
1!
#1020
0!
#1030
b101 &
b101 '
1!
#1040
0!
#1050
b110 &
b110 '
1!
#1060
0!
#1070
b111 &
b111 '
1!
#1080
0!
#1090
b1000 &
b1000 '
1!
#1100
0!
#1110
b1001 &
b1001 '
1!
#1115
0#
#1120
0!
#1130
1!
#1140
0!
#1150
1!
1%
